{
  "rpg_series:root": {
    "criteria": {
      "always": "2025-08-19 22:32:44 +0000"
    },
    "done": true
  },
  "iceandfire:recipes/misc/dragon_ice": {
    "criteria": {
      "has_item": "2025-08-19 22:36:45 +0000"
    },
    "done": true
  },
  "minecraft:recipes/decorations/crafting_table": {
    "criteria": {
      "unlock_right_away": "2025-08-19 22:32:44 +0000"
    },
    "done": true
  },
  "iceandfire:iceandfire/dragonsteel_weapon": {
    "criteria": {
      "sword": "2025-08-19 22:43:36 +0000"
    },
    "done": true
  },
  "iceandfire:recipes/building_blocks/ash": {
    "criteria": {
      "has_item": "2025-08-19 22:36:45 +0000"
    },
    "done": true
  },
  "iceandfire:recipes/misc/skull_to_bone_meal": {
    "criteria": {
      "has_item": "2025-08-19 22:36:45 +0000"
    },
    "done": true
  },
  "iceandfire:iceandfire/root": {
    "criteria": {
      "tick": "2025-08-19 22:32:44 +0000"
    },
    "done": true
  },
  "iceandfire:recipes/food/gold_pile": {
    "criteria": {
      "has_item": "2025-08-19 22:36:45 +0000"
    },
    "done": true
  },
  "minecraft:adventure/root": {
    "criteria": {
      "killed_by_something": "2025-08-19 22:37:12 +0000"
    },
    "done": true
  },
  "regions_unexplored:parent": {
    "criteria": {
      "load_in_world": "2025-08-19 22:32:45 +0000"
    },
    "done": true
  },
  "iceandfire:recipes/misc/dragon_meal": {
    "criteria": {
      "has_item": "2025-08-19 22:36:45 +0000"
    },
    "done": true
  },
  "mobs_of_mythology:mobs_of_mythology": {
    "criteria": {
      "requirement": "2025-08-19 22:32:44 +0000"
    },
    "done": true
  },
  "iceandfire:recipes/misc/blindfold": {
    "criteria": {
      "has_item": "2025-08-19 22:36:45 +0000"
    },
    "done": true
  },
  "rpg_series:misc_items": {
    "criteria": {
      "always": "2025-08-19 22:32:44 +0000"
    },
    "done": true
  },
  "iceandfire:recipes/misc/earplugs": {
    "criteria": {
      "has_item": "2025-08-19 22:36:45 +0000"
    },
    "done": true
  },
  "iceandfire:recipes/decorations/copper_pile": {
    "criteria": {
      "has_item": "2025-08-19 22:36:45 +0000"
    },
    "done": true
  },
  "iceandfire:recipes/misc/copper_nuggets_to_ingot": {
    "criteria": {
      "has_item": "2025-08-19 22:36:45 +0000"
    },
    "done": true
  },
  "iceandfire:recipes/building_blocks/crackled_to_gravel": {
    "criteria": {
      "has_item": "2025-08-19 22:36:45 +0000"
    },
    "done": true
  },
  "regions_unexplored:regions_explored": {
    "criteria": {
      "redwoods": "2025-08-19 22:32:45 +0000"
    },
    "done": false
  },
  "regions_unexplored:pioneer": {
    "criteria": {
      "redwoods": "2025-08-19 22:32:45 +0000"
    },
    "done": false
  },
  "iceandfire:recipes/misc/dragon_stick": {
    "criteria": {
      "has_item": "2025-08-19 22:36:45 +0000"
    },
    "done": true
  },
  "iceandfire:recipes/misc/copper_ingot_to_nuggets": {
    "criteria": {
      "has_item": "2025-08-19 22:36:45 +0000"
    },
    "done": true
  },
  "minecraft:recipes/misc/mojang_banner_pattern": {
    "criteria": {
      "has_enchanted_golden_apple": "2025-08-19 22:41:43 +0000"
    },
    "done": true
  },
  "DataVersion": 3955
}